dash_auth_external/__init__.py
dash_auth_external/auth.py
dash_auth_external/config.py
dash_auth_external/exceptions.py
dash_auth_external/routes.py
dash_auth_external/token.py
tests/__init__.py
tests/test_app.py
tests/test_auth.py
tests/test_config.py
tests/test_context.py
dash_auth_external-1.2.1.dist-info/LICENSE
dash_auth_external-1.2.1.dist-info/METADATA
dash_auth_external-1.2.1.dist-info/WHEEL
dash_auth_external-1.2.1.dist-info/top_level.txt
dash_auth_external-1.2.1.dist-info/RECORD
