Metadata-Version: 2.1
Name: dash-auth-external
Version: 1.2.1
Summary: Integrate your dashboards with 3rd party APIs and external OAuth providers.
Home-page: https://github.com/jamesholcombe/dash-auth-external
Author-email: jholcombe@hotmail.co.uk
Keywords: Dash,Plotly,Authentication,Auth,External
Requires-Python: >=3.7
License-File: LICENSE
Requires-Dist: dash >=2.0.0
Requires-Dist: requests >=1.0.0
Requires-Dist: requests-oauthlib >=0.3.0
